Metadata-Version: 2.1
Name: CatInstaller
Version: 1.7.1
Summary: Catch file, and Installing.
Home-page: http://github.com/diamondgotcat/CatInstaller
Author: TechCat56
Author-email: techcat28@gmail.com
License: MIT
Keywords: Install,Catch,Download
Classifier: Development Status :: 5 - Production/Stable
Classifier: License :: OSI Approved :: MIT License
Classifier: Programming Language :: Python
Classifier: Programming Language :: Python :: 3
Classifier: Programming Language :: Python :: 3.4
Classifier: Programming Language :: Python :: 3.5
Classifier: Programming Language :: Python :: 3.6
Classifier: Topic :: Database
Classifier: Topic :: Software Development :: Libraries :: Python Modules
Requires-Dist: rich
Requires-Dist: requests
